ppser/__init__.py
ppser/predict.py
ppser/trainer.py
ppser/configs/augmentation.yml
ppser/configs/bi_lstm.yml
ppser/data_utils/__init__.py
ppser/data_utils/collate_fn.py
ppser/data_utils/featurizer.py
ppser/data_utils/reader.py
ppser/models/__init__.py
ppser/models/bi_lstm.py
ppser/optimizer/__init__.py
ppser/optimizer/scheduler.py
ppser/utils/__init__.py
ppser/utils/checkpoint.py
ppser/utils/record.py
ppser/utils/utils.py
ppser-0.0.8.dist-info/LICENSE
ppser-0.0.8.dist-info/METADATA
ppser-0.0.8.dist-info/WHEEL
ppser-0.0.8.dist-info/top_level.txt
ppser-0.0.8.dist-info/RECORD
