Metadata-Version: 2.1
Name: ppser
Version: 0.0.8
Summary: Speech Emotion Recognition toolkit on PaddlePaddle
Home-page: https://github.com/yeyupiaoling/SpeechEmotionRecognition-PaddlePaddle
Download-URL: https://github.com/yeyupiaoling/SpeechEmotionRecognition-PaddlePaddle.git
Author: yeyupiaoling
License: Apache License 2.0
Keywords: audio,paddlepaddle,emotion
Platform: UNKNOWN
Classifier: Intended Audience :: Developers
Classifier: License :: OSI Approved :: Apache Software License
Classifier: Operating System :: OS Independent
Classifier: Natural Language :: Chinese (Simplified)
Classifier: Programming Language :: Python :: 3
Classifier: Programming Language :: Python :: 3.5
Classifier: Programming Language :: Python :: 3.6
Classifier: Programming Language :: Python :: 3.7
Classifier: Programming Language :: Python :: 3.8
Classifier: Programming Language :: Python :: 3.9
Classifier: Topic :: Utilities
License-File: LICENSE
Requires-Dist: numpy (>=1.19.2)
Requires-Dist: scipy (>=1.6.3)
Requires-Dist: librosa (~=0.9.1)
Requires-Dist: soundfile (>=0.12.1)
Requires-Dist: soundcard (>=0.4.2)
Requires-Dist: resampy (>=0.2.2)
Requires-Dist: numba (>=0.53.0)
Requires-Dist: pydub (~=0.25.1)
Requires-Dist: matplotlib (>=3.5.2)
Requires-Dist: pillow (>=8.3.2)
Requires-Dist: tqdm (>=4.64.1)
Requires-Dist: visualdl (>=2.2.3)
Requires-Dist: pyyaml (>=5.4.1)
Requires-Dist: scikit-learn (>=1.0.2)
Requires-Dist: av (>=10.0.0)
Requires-Dist: joblib (>=1.2.0)
Requires-Dist: loguru (>=0.7.2)
Requires-Dist: yeaudio (>=0.0.2)
